gsppy/__init__.py
gsppy/accelerate.py
gsppy/cli.py
gsppy/dataframe_adapters.py
gsppy/enums.py
gsppy/gsp.py
gsppy/pruning.py
gsppy/py.typed
gsppy/sequence.py
gsppy/token_mapper.py
gsppy/utils.py
gsppy-4.1.0.dist-info/METADATA
gsppy-4.1.0.dist-info/WHEEL
gsppy-4.1.0.dist-info/entry_points.txt
gsppy-4.1.0.dist-info/licenses/LICENSE
gsppy-4.1.0.dist-info/RECORD
