Metadata-Version: 2.4
Name: gsppy
Version: 4.1.0
Summary: GSP (Generalized Sequence Pattern) algorithm in Python
Project-URL: Homepage, https://github.com/jacksonpradolima/gsp-py
Author-email: Jackson Antonio do Prado Lima <jacksonpradolima@gmail.com>
Maintainer-email: Jackson Antonio do Prado Lima <jacksonpradolima@gmail.com>
License: MIT License
License-File: LICENSE
Keywords: GSP,data analysis,sequence mining,sequential patterns
Classifier: Intended Audience :: Science/Research
Classifier: License :: OSI Approved :: MIT License
Classifier: Natural Language :: English
Classifier: Operating System :: OS Independent
Classifier: Programming Language :: Python :: 3.11
Classifier: Programming Language :: Python :: 3.12
Classifier: Programming Language :: Python :: 3.13
Classifier: Programming Language :: Python :: 3.14
Classifier: Topic :: Scientific/Engineering :: Information Analysis
Classifier: Topic :: Software Development :: Libraries :: Python Modules
Requires-Python: >=3.11
Requires-Dist: click>=8.0.0
Requires-Dist: typing-extensions>=4.0.0
Provides-Extra: dataframe
Requires-Dist: pandas-stubs>=2.3.3.260113; extra == 'dataframe'
Requires-Dist: pandas>=3.0.0; extra == 'dataframe'
Requires-Dist: polars>=1.37.1; extra == 'dataframe'
Requires-Dist: pyarrow>=10.0.0; extra == 'dataframe'
Provides-Extra: dev
Requires-Dist: cython==3.2.4; extra == 'dev'
Requires-Dist: hatch==1.16.3; extra == 'dev'
Requires-Dist: hatchling==1.28.0; extra == 'dev'
Requires-Dist: hypothesis<7.0.0,>=6.0.0; extra == 'dev'
Requires-Dist: pylint==4.0.4; extra == 'dev'
Requires-Dist: pyright==1.1.408; extra == 'dev'
Requires-Dist: pytest-benchmark==5.2.3; extra == 'dev'
Requires-Dist: pytest-cov==7.0.0; extra == 'dev'
Requires-Dist: pytest==9.0.2; extra == 'dev'
Requires-Dist: ruff==0.14.14; extra == 'dev'
Requires-Dist: tox==4.34.1; extra == 'dev'
Requires-Dist: ty==0.0.14; extra == 'dev'
Provides-Extra: docs
Requires-Dist: mkdocs-gen-files<1,>=0.5; extra == 'docs'
Requires-Dist: mkdocs-literate-nav<1,>=0.6; extra == 'docs'
Requires-Dist: mkdocs-material<10,>=9.5; extra == 'docs'
Requires-Dist: mkdocs<2,>=1.6; extra == 'docs'
Requires-Dist: mkdocstrings[python]<1.1,>=0.26; extra == 'docs'
Provides-Extra: gpu
Requires-Dist: cupy<14,>=11; extra == 'gpu'
Provides-Extra: rust
Requires-Dist: maturin==1.11.5; extra == 'rust'
